roconfiguration/__init__.py
roconfiguration-1.0.9.dist-info/LICENSE
roconfiguration-1.0.9.dist-info/METADATA
roconfiguration-1.0.9.dist-info/WHEEL
roconfiguration-1.0.9.dist-info/top_level.txt
roconfiguration-1.0.9.dist-info/RECORD
