Metadata-Version: 2.1
Name: roconfiguration
Version: 1.0.9
Summary: Implementation of key-value pair based configuration for Python applications.
Home-page: https://github.com/Neoteroi/roconfiguration
Author: RobertoPrevato
Author-email: roberto.prevato@gmail.com
License: MIT
Keywords: configuration root core yaml ini json environment
Platform: UNKNOWN
Classifier: Development Status :: 5 - Production/Stable
Classifier: License :: OSI Approved :: MIT License
Classifier: Programming Language :: Python :: 3
Classifier: Programming Language :: Python :: 3.6
Classifier: Programming Language :: Python :: 3.7
Classifier: Programming Language :: Python :: 3.8
Classifier: Programming Language :: Python :: 3.9
Classifier: Programming Language :: Python :: 3.10
Classifier: Operating System :: OS Independent
License-File: LICENSE
Requires-Dist: PyYAML (==5.4.1)
